AUTHORS.rst
CONTRIBUTING.rst
HISTORY.rst
LICENSE
MANIFEST.in
README.md
setup.cfg
setup.py
bin/autotaxonomy
bin/percent_identity_vs_tree_distance
bin/threshold_estimator
bin/tree2tax
docs/Makefile
docs/authors.rst
docs/conf.py
docs/contributing.rst
docs/history.rst
docs/index.rst
docs/installation.rst
docs/make.bat
docs/readme.rst
docs/usage.rst
tests/test_threshold_finder.py
tests/test_tree2tax.py
tree2tax/__init__.py
tree2tax/threshold_finder.py
tree2tax/tree2tax.py
tree2tax/version.py
tree2tax.egg-info/PKG-INFO
tree2tax.egg-info/SOURCES.txt
tree2tax.egg-info/dependency_links.txt
tree2tax.egg-info/not-zip-safe
tree2tax.egg-info/requires.txt
tree2tax.egg-info/top_level.txt