Metadata-Version: 1.1
Name: tree2tax
Version: 0.1.2
Summary: Automatic taxonomy through consistent application of tree-based thresholding
Home-page: https://github.com/wwood/tree2tax
Author: Ben Woodcroft
Author-email: b.woodcroft near uq.edu.au
License: LGPL3
Keywords: tree2tax
Platform: UNKNOWN
Classifier: Development Status :: 2 - Pre-Alpha
Classifier: Intended Audience :: Developers
Classifier: License :: OSI Approved :: BSD License
Classifier: Natural Language :: English
Classifier: Programming Language :: Python :: 2
Classifier: Programming Language :: Python :: 2.6
Classifier: Programming Language :: Python :: 2.7
Classifier: Programming Language :: Python :: 3
Classifier: Programming Language :: Python :: 3.3
Classifier: Programming Language :: Python :: 3.4
